[{"name":"Professores da UFCG","description":"Comunidade para professores da UFCG","manager":"jpsauve","members":["jpsauve"]},{"name":"UFCG","description":"Comunidade para professores, alunos e funcionários da UFCG","manager":"jpsauve","members":["jpsauve"]},{"name":"UFCG2","description":"Comunidade para professores, alunos e funcionários da UFCG","manager":"jpsauve","members":["jpsauve"]},{"name":"Alunos da UFCG","description":"Comunidade para alunos da UFCG","manager":"oabath","members":["oabath"]}]